myprn_026/__init__.py
myprn_026-0.1.dist-info/METADATA
myprn_026-0.1.dist-info/WHEEL
myprn_026-0.1.dist-info/license.txt
myprn_026-0.1.dist-info/top_level.txt
myprn_026-0.1.dist-info/RECORD
