Metadata-Version: 2.1
Name: myprn-026
Version: 0.1
Summary: for multiplying two values
Author: Nishant
Author-email: nishantbadgujar2609@gmail.com
Classifier: Programming Language :: Python :: 3
Classifier: License :: OSI Approved :: MIT License
Classifier: Operating System :: OS Independent
License-File: license.txt
